cw_constrain/__init__.py
cw_constrain/DM_constrain/__init__.py
cw_constrain/DM_constrain/dm_constrain.py
cw_constrain/GeV_constrain/__init__.py
cw_constrain/GeV_constrain/gev_constrain.py
cw_constrain/GeV_constrain/data/pulsar_data_atnf_f0_fdots_dist_Bfield_type_age.csv
cw_constrain/GeV_constrain/data/ellipticity_distributions/atnf_ellip_1perc_1e38_.txt
cw_constrain/GeV_constrain/data/freq_distributions/atnf_freq_ex.txt
cw_constrain/GeV_constrain/data/lum_funcs/Lumin.csv
cw_constrain/GeV_constrain/data/lum_funcs/Lumin.nb
cw_constrain/GeV_constrain/data/lum_funcs/eta-ar.txt
cw_constrain/GeV_constrain/data/lum_funcs/eta-br.txt
cw_constrain/GeV_constrain/data/lum_funcs/eta-dr.txt
cw_constrain/GeV_constrain/data/lum_funcs/lumin.txt
cw_constrain/PBH_constrain/__init__.py
cw_constrain/PBH_constrain/pbh_constrain.py
cw_constrain/shared/__init__.py
cw_constrain/shared/shared_utils.py
cw_constrain-0.1.4.dist-info/METADATA
cw_constrain-0.1.4.dist-info/WHEEL
cw_constrain-0.1.4.dist-info/RECORD
