Metadata-Version: 2.4
Name: cw_constrain
Version: 0.1.4
Summary: Tools to constrain PBHs and the GeV excess using continuous gravitational waves
Project-URL: Homepage, https://github.com/andrew-l-miller/cw_constrain
Project-URL: Issues, https://github.com/andrew-l-miller/cw_constrain/issues
Project-URL: Documentation, https://github.com/andrew-l-miller/cw_constrain#readme
Project-URL: DOI, https://doi.org/10.5281/zenodo.15559328
Author-email: "Andrew L. Miller" <andrew.miller.ligo@gmail.com>
License-Expression: MIT AND (Apache-2.0 OR BSD-2-Clause)
Classifier: License :: OSI Approved :: MIT License
Classifier: Operating System :: OS Independent
Classifier: Programming Language :: Python :: 3
Requires-Python: >=3.8
Requires-Dist: astropy
Requires-Dist: matplotlib
Requires-Dist: numpy
Requires-Dist: pandas
Requires-Dist: scipy
